staticbuilder
tests
