Metadata-Version: 1.1
Name: django-staticbuilder
Version: 0.6.3
Summary: Optimize your static files.
Home-page: http://github.com/hzdg/django-staticbuilder
Author: Matthew Tretter
Author-email: m@tthewwithanm.com
License: UNKNOWN
Download-URL: http://github.com/hzdg/django-staticbuilder/tarball/master
Keywords: javascript,css,compressor,requirejs
Platform: UNKNOWN
Classifier: Environment :: Web Environment
Classifier: Framework :: Django
Classifier: Intended Audience :: Developers
Classifier: License :: OSI Approved :: BSD License
Classifier: Operating System :: OS Independent
Classifier: Programming Language :: Python :: 2.5
Classifier: Programming Language :: Python :: 2.6
Classifier: Programming Language :: Python :: 2.7
Classifier: Programming Language :: Python :: 3.2
Classifier: Programming Language :: Python :: 3.3
Classifier: Topic :: Utilities
